thiscovery_lib/__init__.py
thiscovery_lib/core_api_utilities.py
thiscovery_lib/countries.json
thiscovery_lib/dynamodb_utilities.py
thiscovery_lib/eb_utilities.py
thiscovery_lib/emails_api_utilities.py
thiscovery_lib/entity_base.py
thiscovery_lib/hubspot_utilities.py
thiscovery_lib/interviews_api_utilities.py
thiscovery_lib/lambda_utilities.py
thiscovery_lib/notification_send.py
thiscovery_lib/notifications.py
thiscovery_lib/qualtrics.py
thiscovery_lib/s3_utilities.py
thiscovery_lib/ses_utilities.py
thiscovery_lib/surveys_api_utilities.py
thiscovery_lib/thiscovery_api_utilities.py
thiscovery_lib/utilities.py
thiscovery_lib-2021.2.3.dist-info/LICENSE
thiscovery_lib-2021.2.3.dist-info/METADATA
thiscovery_lib-2021.2.3.dist-info/WHEEL
thiscovery_lib-2021.2.3.dist-info/top_level.txt
thiscovery_lib-2021.2.3.dist-info/RECORD
