Metadata-Version: 2.1
Name: thiscovery-lib
Version: 2021.2.3
Summary: Thiscovery library
Home-page: https://github.com/THIS-Institute/thiscovery-lib
Author: Thiscovery team
Author-email: support@thiscovery.org
License: UNKNOWN
Platform: UNKNOWN
Classifier: Programming Language :: Python :: 3
Classifier: License :: OSI Approved :: GNU Affero General Public License v3
Classifier: Operating System :: OS Independent
Requires-Python: >=3.6
Requires-Dist: boto3
Requires-Dist: botocore
Requires-Dist: python-dateutil
Requires-Dist: epsagon
Requires-Dist: jsons
Requires-Dist: python-json-logger
Requires-Dist: requests
Requires-Dist: validators
